crimson/pymongo_bridge/__init__.py
crimson/pymongo_bridge/simple_chatbot.py
crimson_pymongo_bridge-0.1.1.dist-info/LICENSE
crimson_pymongo_bridge-0.1.1.dist-info/METADATA
crimson_pymongo_bridge-0.1.1.dist-info/WHEEL
crimson_pymongo_bridge-0.1.1.dist-info/top_level.txt
crimson_pymongo_bridge-0.1.1.dist-info/RECORD
